netbox_documents/__init__.py
netbox_documents/filtersets.py
netbox_documents/forms.py
netbox_documents/models.py
netbox_documents/navigation.py
netbox_documents/search.py
netbox_documents/tables.py
netbox_documents/template_content.py
netbox_documents/urls.py
netbox_documents/utils.py
netbox_documents/views.py
netbox_documents/api/__init__.py
netbox_documents/api/fields.py
netbox_documents/api/serializers.py
netbox_documents/api/urls.py
netbox_documents/api/views.py
netbox_documents/migrations/0001_initial.py
netbox_documents/migrations/0002_AddDeviceType.py
netbox_documents/migrations/0003_alter_circuitdocument_options_and_more.py
netbox_documents/migrations/0004_locationdocument.py
netbox_documents/migrations/0005_alter_circuitdocument_external_url_and_more.py
netbox_documents/migrations/0006_vmdocument.py
netbox_documents/migrations/0007_circuitproviderdocument.py
netbox_documents/migrations/0008_moduletypedocument.py
netbox_documents/migrations/__init__.py
netbox_documents/templates/netbox_documents/circuitdocument.html
netbox_documents/templates/netbox_documents/circuitdocument_edit.html
netbox_documents/templates/netbox_documents/circuitdocument_include.html
netbox_documents/templates/netbox_documents/circuitproviderdocument.html
netbox_documents/templates/netbox_documents/circuitproviderdocument_edit.html
netbox_documents/templates/netbox_documents/circuitproviderdocument_include.html
netbox_documents/templates/netbox_documents/devicedocument.html
netbox_documents/templates/netbox_documents/devicedocument_edit.html
netbox_documents/templates/netbox_documents/devicedocument_include.html
netbox_documents/templates/netbox_documents/devicetypedocument.html
netbox_documents/templates/netbox_documents/devicetypedocument_edit.html
netbox_documents/templates/netbox_documents/devicetypedocument_include.html
netbox_documents/templates/netbox_documents/document_edit.html
netbox_documents/templates/netbox_documents/locationdocument.html
netbox_documents-0.7.4.dist-info/licenses/LICENSE
netbox_documents-0.7.4.dist-info/METADATA
netbox_documents-0.7.4.dist-info/WHEEL
netbox_documents-0.7.4.dist-info/top_level.txt
netbox_documents-0.7.4.dist-info/RECORD
