Metadata-Version: 2.4
Name: netbox-documents
Version: 0.7.4
Summary: Manage site, location, circuit and device diagrams and documents in Netbox
Home-page: https://github.com/jasonyates/netbox-documents
Author: Jason Yates
Author-email: me@jasonyates.co.uk
Keywords: netbox,netbox-plugin,plugin
License-File: LICENSE
Requires-Dist: drf_extra_fields>=3.7.0
Dynamic: author
Dynamic: author-email
Dynamic: description
Dynamic: description-content-type
Dynamic: home-page
Dynamic: keywords
Dynamic: license-file
Dynamic: requires-dist
Dynamic: summary
